cooputils/__init__.py
cooputils/config.py
cooputils/eleven_labs.py
cooputils/llms.py
cooputils-0.2.0.dist-info/METADATA
cooputils-0.2.0.dist-info/WHEEL
cooputils-0.2.0.dist-info/top_level.txt
cooputils-0.2.0.dist-info/RECORD
