Metadata-Version: 2.2
Name: cooputils
Version: 0.2.0
Requires-Dist: modal
Requires-Dist: openai
Requires-Dist: python-dotenv
Requires-Dist: pydantic
Requires-Dist: instructor
Requires-Dist: requests
Dynamic: description
Dynamic: description-content-type
Dynamic: requires-dist
